yodi_umbaji/__init__.py
yodi_umbaji/main.py
yodi_umbaji-0.5.6.dist-info/LICENSE
yodi_umbaji-0.5.6.dist-info/METADATA
yodi_umbaji-0.5.6.dist-info/WHEEL
yodi_umbaji-0.5.6.dist-info/top_level.txt
yodi_umbaji-0.5.6.dist-info/RECORD
