Metadata-Version: 2.1
Name: yodi_umbaji
Version: 0.5.6
License-File: LICENSE
Requires-Dist: pathlib
Requires-Dist: tensorflow
Requires-Dist: matplotlib
Requires-Dist: numpy
Requires-Dist: seaborn
Requires-Dist: IPython
Requires-Dist: gradio
